flatlib/__init__.py
flatlib/angle.py
flatlib/aspects.py
flatlib/chart.py
flatlib/const.py
flatlib/datetime.py
flatlib/geopos.py
flatlib/lists.py
flatlib/object.py
flatlib/props.py
flatlib/utils.py
flatlib/dignities/__init__.py
flatlib/dignities/accidental.py
flatlib/dignities/essential.py
flatlib/dignities/tables.py
flatlib/ephem/__init__.py
flatlib/ephem/eph.py
flatlib/ephem/ephem.py
flatlib/ephem/swe.py
flatlib/ephem/tools.py
flatlib/predictives/__init__.py
flatlib/predictives/primarydirections.py
flatlib/predictives/profections.py
flatlib/predictives/returns.py
flatlib/protocols/__init__.py
flatlib/protocols/almutem.py
flatlib/protocols/behavior.py
flatlib/protocols/temperament.py
flatlib/resources/README.md
flatlib/resources/swefiles/fixstars.cat
flatlib/resources/swefiles/seas_12.se1
flatlib/resources/swefiles/seas_18.se1
flatlib/resources/swefiles/seas_24.se1
flatlib/resources/swefiles/sefstars.txt
flatlib/resources/swefiles/semo_12.se1
flatlib/resources/swefiles/semo_18.se1
flatlib/resources/swefiles/semo_24.se1
flatlib/resources/swefiles/sepl_12.se1
flatlib/resources/swefiles/sepl_18.se1
flatlib/resources/swefiles/sepl_24.se1
flatlib/tools/__init__.py
flatlib/tools/arabicparts.py
flatlib/tools/chartdynamics.py
flatlib/tools/planetarytime.py
flatlib-0.2.3.dist-info/LICENSE
flatlib-0.2.3.dist-info/METADATA
flatlib-0.2.3.dist-info/WHEEL
flatlib-0.2.3.dist-info/top_level.txt
flatlib-0.2.3.dist-info/RECORD
